click_logging_config/VERSION
click_logging_config/__init__.py
click_logging_config/_click.py
click_logging_config/_default_values.py
click_logging_config/_logging.py
click_logging_config/_version.py
click_logging_config/parameters.py
click_logging_config/py.typed
click_logging_config-2.1.1.dist-info/METADATA
click_logging_config-2.1.1.dist-info/WHEEL
click_logging_config-2.1.1.dist-info/licenses/LICENSE.txt
click_logging_config-2.1.1.dist-info/RECORD
