Metadata-Version: 2.4
Name: click_logging_config
Version: 2.1.1
Dynamic: Summary
Project-URL: source, https://gitlab.com/ci-cd-devops/click_logging_config
Author-email: Russell Smiley <russell@bytingchipmunk.com>
License-Expression: MIT
License-File: LICENSE.txt
Classifier: Intended Audience :: Developers
Classifier: Programming Language :: Python :: 3 :: Only
Classifier: Typing :: Typed
Requires-Python: >=3.10
Requires-Dist: click>=8.3
Requires-Dist: json-log-formatter>=1.0
Requires-Dist: pendulum>=3.1
Requires-Dist: pydantic<3,>=2
Requires-Dist: pytz>=2025.2
Provides-Extra: dev
Requires-Dist: invoke>=2.2.0; extra == 'dev'
Requires-Dist: mypy>=1.18.2; extra == 'dev'
Requires-Dist: pre-commit>=4.3; extra == 'dev'
Requires-Dist: ruff>=0.14.4; extra == 'dev'
Requires-Dist: types-pytz>=2025.2; extra == 'dev'
Requires-Dist: uv>=0.9.8; extra == 'dev'
Provides-Extra: doc
Requires-Dist: sphinx-rtd-theme>=2.0; extra == 'doc'
Requires-Dist: sphinx>=7.4.7; extra == 'doc'
Provides-Extra: rich-click
Requires-Dist: rich-click>=1.8; extra == 'rich-click'
Provides-Extra: test
Requires-Dist: pytest-cov>=7.0; extra == 'test'
Requires-Dist: pytest-mock>=3.15.1; extra == 'test'
Requires-Dist: pytest>=8.4.2; extra == 'test'
